docker_evolve/__init__.py
docker_evolve/__main__.py
docker_evolve/py.typed
docker_evolve-0.1.0.dist-info/entry_points.txt
docker_evolve-0.1.0.dist-info/LICENSE
docker_evolve-0.1.0.dist-info/WHEEL
docker_evolve-0.1.0.dist-info/METADATA
docker_evolve-0.1.0.dist-info/RECORD
